cherab_nagdis-0.1.1.dist-info/RECORD
cherab_nagdis-0.1.1.dist-info/WHEEL
cherab_nagdis-0.1.1.dist-info/METADATA
cherab_nagdis-0.1.1.dist-info/licenses/LICENSE
cherab/nagdis/__init__.py
cherab/nagdis/tools/fetch.py
cherab/nagdis/tools/__init__.py
cherab/nagdis/tools/visualize.py
cherab/nagdis/tools/emission.py
cherab/nagdis/inversion/__init__.py
cherab/nagdis/inversion/utils.py
cherab/nagdis/inversion/raytransfer.py
cherab/nagdis/inversion/mlem.py
cherab/nagdis/machine/nagdis_ii.py
cherab/nagdis/machine/__init__.py
cherab/nagdis/machine/material/__init__.py
cherab/nagdis/machine/material/roughmetal.py
cherab/nagdis/machine/material/metal.py
cherab/nagdis/experiment/__init__.py
cherab/nagdis/experiment/dataset.py
cherab/nagdis/experiment/utils.py
cherab/nagdis/experiment/conditional_average.py
cherab/nagdis/observers/thin_lens_ccd.cpython-312-darwin.so
cherab/nagdis/observers/__init__.py
cherab/nagdis/observers/camera.py
cherab/nagdis/observers/thin_lens_ccd.cpython-311-darwin.so
cherab/nagdis/observers/thin_lens_ccd.cpython-310-darwin.so
