Metadata-Version: 2.4
Name: cherab-nagdis
Version: 0.1.1
Summary: Cherab for NAGDIS-II
Author-email: Koyo Munechika <munechika.koyo@gmail.com>
License: MIT
License-File: LICENSE
Keywords: cherab,fusion,inversion,nagdis,plasma
Classifier: Development Status :: 4 - Beta
Classifier: Programming Language :: Python
Classifier: Programming Language :: Python :: 3.10
Classifier: Programming Language :: Python :: 3.11
Classifier: Programming Language :: Python :: 3.12
Classifier: Programming Language :: Python :: 3.13
Classifier: Programming Language :: Python :: Implementation :: CPython
Requires-Python: >=3.10
Requires-Dist: calcam
Requires-Dist: cherab
Requires-Dist: matplotlib
Requires-Dist: numpy
Requires-Dist: paramiko
Requires-Dist: plotly
Requires-Dist: pooch
Requires-Dist: rich
Requires-Dist: scipy
Requires-Dist: tqdm
